{
  "$schema": "vault",
  "comment": "WBTC",
  "hideAlways": false,
  "depositsDisabled": true,
  "withdrawalsDisabled": false,
  "order": 49,
  "migrationAvailable": true,
  "migrationContract": "0xC53f28C40de7FdD184ebecC94de2d3DB5E3234eB",
  "migrationTargetVault": "0x7Edf16076e56FA4c111055fbA1fF5556b8757cFB",
  "allowZapIn": false,
  "allowZapOut": true,
  "retired": false,
  "displayName": "WBTC",
  "classification": {
    "isAutomated": false,
    "isPool": false,
    "stability": "Stable",
    "stableBaseAsset": "Bitcoin"
  }
}
